{"brickPackages":[{"id":"bricks/basic","bricks":["basic.active-element-blur","basic.change-language","basic.copy-to-clipboard","basic.get-language","basic.http-proxy-request","basic.http-request","basic.set-theme-by-apps","basic.set-timeout","basic.general-button","basic.general-link","basic.general-text","basic.general-image","basic.dropdown-button","basic.general-popover","basic.general-menu","basic.general-menu-item","basic.general-tag","basic.general-tag-list","basic.app-bar-wrapper","basic.v3-widget-mate","basic.lock-body-scroll","basic.show-watermark","basic.home-redirect","basic.show-dialog","basic.show-notification"],"elements":["eo-button","eo-link","eo-text","eo-image","eo-dropdown-button","eo-popover","eo-menu","eo-menu-item","eo-tag","eo-tag-list","eo-mini-actions","eo-tooltip","eo-dropdown-actions","eo-avatar","eo-sidebar-sub-menu","eo-menu-item-sub-menu","eo-menu-group","eo-breadcrumb-item","eo-breadcrumb","eo-frame-breadcrumb","eo-sidebar-menu-item","eo-sidebar-menu-group","eo-sidebar-menu-submenu","eo-sidebar-menu","eo-sidebar","eo-app-bar-wrapper","eo-page-title","eo-counter-badge","eo-easyops-avatar","eo-avatar-group","eo-actions","eo-context-menu","eo-formatter-number","eo-event-agent","eo-message-listener","eo-broadcast-channel","eo-iframe"],"processors":[],"editors":["eo-button","eo-submit-buttons","eo-text","eo-search-bar","eo-spin","eo-tag","eo-popover","eo-search","eo-category","eo-input","eo-checkbox","eo-form","eo-radio","eo-select","eo-switch","eo-textarea","eo-tab-list","eo-drawer","eo-divider","eo-modal","eo-card-item","eo-link","eo-mini-actions","eo-flex-layout","eo-grid-layout","eo-easy-view","eo-next-table","eo-descriptions","eo-alert"],"dependencies":{"eo-button":["eo-link","eo-tooltip","eo-icon"],"basic.general-button":["eo-link","eo-tooltip","eo-icon"],"eo-link":["eo-icon","eo-tooltip"],"basic.general-link":["eo-icon","eo-tooltip"],"eo-text":["eo-link","eo-input","eo-textarea","eo-icon","eo-tooltip"],"basic.general-text":["eo-link","eo-input","eo-textarea","eo-icon","eo-tooltip"],"eo-image":["eo-icon"],"basic.general-image":["eo-icon"],"eo-dropdown-button":["eo-button","eo-dropdown-actions"],"basic.dropdown-button":["eo-button","eo-dropdown-actions"],"eo-popover":["sl-popup"],"basic.general-popover":["sl-popup"],"eo-menu-item":["eo-icon"],"basic.general-menu-item":["eo-icon"],"eo-tag":["eo-icon"],"basic.general-tag":["eo-icon"],"eo-tag-list":["eo-icon","eo-tag"],"basic.general-tag-list":["eo-icon","eo-tag"],"eo-mini-actions":["eo-tooltip","eo-icon","eo-link","eo-popover","eo-actions"],"eo-tooltip":["eo-icon","sl-tooltip"],"eo-dropdown-actions":["eo-popover","eo-actions"],"eo-avatar":["eo-icon","sl-resize-observer"],"eo-sidebar-sub-menu":["eo-icon","eo-menu","eo-menu-group","eo-menu-item-sub-menu","eo-menu-item","eo-link","eo-tooltip"],"eo-menu-item-sub-menu":["eo-icon"],"eo-breadcrumb-item":["eo-link"],"eo-breadcrumb":["eo-link"],"eo-frame-breadcrumb":["eo-breadcrumb","eo-breadcrumb-item","eo-icon"],"eo-sidebar-menu-item":["eo-link","eo-icon"],"eo-sidebar-menu-group":["eo-sidebar-menu","eo-sidebar-menu-item","eo-sidebar-menu-submenu"],"eo-sidebar-menu-submenu":["eo-icon","eo-sidebar-menu","eo-sidebar-menu-item","eo-sidebar-menu-group"],"eo-sidebar-menu":["eo-sidebar-menu-item","eo-sidebar-menu-group","eo-sidebar-menu-submenu"],"eo-sidebar":["eo-tooltip","eo-icon","eo-sidebar-menu","eo-sidebar-menu-item","eo-sidebar-menu-group","eo-sidebar-menu-submenu"],"eo-counter-badge":["eo-icon"],"eo-easyops-avatar":["eo-avatar"],"eo-avatar-group":["eo-icon","sl-resize-observer"],"eo-actions":["eo-tooltip","eo-link","eo-menu","eo-menu-item","eo-popover"],"eo-context-menu":["basic.lock-body-scroll","eo-actions"],"basic.show-dialog":["eo-button","eo-antd-icon","eo-input","sl-dialog"],"basic.show-notification":["eo-icon","eo-link","sl-alert"]},"filePath":"/preview/bricks/basic/dist/index.11f9ce69.js","deprecatedElements":["eo-app-bar-wrapper","eo-frame-breadcrumb","eo-sidebar","eo-sidebar-menu-item","eo-sidebar-menu-group","eo-sidebar-menu","eo-sidebar-sub-menu","eo-sidebar-menu-submenu"]},{"id":"bricks/containers","bricks":["containers.micro-view","containers.general-category","containers.general-modal","containers.general-card","containers.general-drawer","containers.grid-layout","containers.flex-layout","containers.easy-view","containers.search-bar","containers.tab-group","containers.tab-item","containers.tab-list"],"elements":["eo-micro-view","eo-category","eo-modal","eo-card","eo-drawer","eo-grid-layout","eo-flex-layout","eo-easy-view","eo-spin","eo-search-bar","eo-content-layout","eo-popup","eo-resizable-box","eo-tab-group","eo-tab-item","eo-tab-list","eo-page-view","eo-main-view","eo-narrow-view","eo-banner"],"processors":[],"editors":["eo-card"],"dependencies":{"eo-micro-view":["eo-page-title"],"containers.micro-view":["eo-page-title"],"eo-modal":["basic.lock-body-scroll","eo-button","eo-icon"],"containers.general-modal":["basic.lock-body-scroll","eo-button","eo-icon"],"eo-card":["eo-button","eo-icon"],"containers.general-card":["eo-button","eo-icon"],"eo-drawer":["basic.lock-body-scroll","eo-icon"],"containers.general-drawer":["basic.lock-body-scroll","eo-icon"],"eo-popup":["eo-icon"],"eo-tab-item":["eo-counter-badge","eo-icon"],"containers.tab-item":["eo-counter-badge","eo-icon"],"eo-tab-list":["eo-tab-group","eo-tab-item"],"containers.tab-list":["eo-tab-group","eo-tab-item"],"eo-main-view":["eo-page-title"],"eo-banner":["eo-page-title"]},"filePath":"/preview/bricks/containers/dist/index.5d84606b.js"},{"id":"bricks/form","bricks":["form.general-input","form.general-textarea","form.general-form-item","form.general-form","form.general-radio","form.general-select","form.submit-buttons","form.general-checkbox","form.dynamic-form-item","form.general-search","form.icon-select","form.general-switch","form.upload-image"],"elements":["eo-input","eo-textarea","eo-form-item","eo-form","eo-radio","eo-select","eo-submit-buttons","eo-checkbox","eo-dynamic-form-item","eo-search","eo-icon-select","eo-switch","eo-upload-image","eo-upload-file","eo-auto-complete","eo-time-picker","eo-date-picker","eo-time-range-picker","eo-color-picker"],"processors":[],"editors":[],"dependencies":{"eo-input":["eo-icon","eo-form-item"],"form.general-input":["eo-icon","eo-form-item"],"eo-textarea":["eo-form-item"],"form.general-textarea":["eo-form-item"],"eo-radio":["eo-icon","eo-form-item"],"form.general-radio":["eo-icon","eo-form-item"],"eo-select":["eo-form-item","eo-tag","eo-icon"],"form.general-select":["eo-form-item","eo-tag","eo-icon"],"eo-submit-buttons":["eo-form-item","eo-button"],"form.submit-buttons":["eo-form-item","eo-button"],"eo-checkbox":["eo-form-item","eo-icon"],"form.general-checkbox":["eo-form-item","eo-icon"],"eo-dynamic-form-item":["eo-icon","eo-button","eo-form","eo-form-item"],"form.dynamic-form-item":["eo-icon","eo-button","eo-form","eo-form-item"],"eo-search":["eo-icon","eo-input","eo-form-item"],"form.general-search":["eo-icon","eo-input","eo-form-item"],"eo-icon-select":["icons.get-libs","icons.search-icons","eo-radio","eo-icon","eo-modal","eo-search","eo-form-item"],"form.icon-select":["icons.get-libs","icons.search-icons","eo-radio","eo-icon","eo-modal","eo-search","eo-form-item"],"eo-switch":["eo-form-item","eo-icon"],"form.general-switch":["eo-form-item","eo-icon"],"eo-upload-image":["eo-button","eo-image","eo-icon","eo-form-item"],"form.upload-image":["eo-button","eo-image","eo-icon","eo-form-item"],"eo-upload-file":["eo-button","eo-icon","eo-easyops-icon","eo-tooltip","eo-form-item"],"eo-auto-complete":["eo-form-item","eo-input","eo-icon"],"eo-time-picker":["eo-form-item"],"eo-date-picker":["eo-form-item","eo-icon"],"eo-time-range-picker":["eo-form-item","eo-icon"],"eo-color-picker":["eo-form-item"]},"filePath":"/preview/bricks/form/dist/index.8e3bfb8e.js"},{"id":"bricks/icons","bricks":["icons.get-easyops-icons","icons.get-fa-icons","icons.get-antd-icons","icons.get-libs","icons.search-icons","icons.antd-icon","icons.easyops-icon","icons.fa-icon","icons.general-icon"],"elements":["eo-antd-icon","eo-easyops-icon","eo-fa-icon","eo-img-icon","eo-svg-icon","eo-icon"],"processors":[],"editors":["eo-icon"],"dependencies":{},"filePath":"/preview/bricks/icons/dist/index.ae7fb4d1.js"},{"id":"bricks/shoelace","bricks":[],"elements":["sl-alert","sl-animated-image","sl-animation","sl-avatar","sl-badge","sl-breadcrumb","sl-breadcrumb-item","sl-button-group","sl-button","sl-card","sl-carousel","sl-carousel-item","sl-checkbox","sl-color-picker","sl-details","sl-dialog","sl-divider","sl-drawer","sl-dropdown","sl-format-bytes","sl-format-date","sl-format-number","sl-icon-button","sl-icon","sl-image-comparer","sl-input","sl-menu-label","sl-menu","sl-menu-item","sl-mutation-observer","sl-option","sl-popup","sl-progress-bar","sl-progress-ring","sl-qr-code","sl-radio-button","sl-radio-group","sl-radio","sl-range","sl-rating","sl-relative-time","sl-resize-observer","sl-select","sl-skeleton","sl-spinner","sl-split-panel","sl-switch","sl-tab-group","sl-tab","sl-tab-panel","sl-tag","sl-textarea","sl-tooltip","sl-tree","sl-tree-item","sl-visually-hidden"],"processors":[],"editors":[],"dependencies":{},"filePath":"/preview/bricks/shoelace/dist/index.ab1f6661.js"}],"settings":{"misc":{"weather_api_key":"9e08e5e99e0c4b4c89023605231804"}}}